roborambo/__init__.py
roborambo/__main__.py
roborambo/assistant.py
roborambo/cli.py
roborambo/config.py
roborambo/daemon.py
roborambo/memory.py
roborambo/types.py
roborambo/chains/__init__.py
roborambo/chains/rambo.py
roborambo/interfaces/__init__.py
roborambo/interfaces/cli.py
roborambo/interfaces/discord.py
roborambo/interfaces/googlechat.py
roborambo/interfaces/matrix.py
roborambo/interfaces/mattermost.py
roborambo/interfaces/messaging.py
roborambo/interfaces/rocketchat.py
roborambo/interfaces/teams.py
roborambo/interfaces/web.py
roborambo/interfaces/zulip.py
roborambo/tools/__init__.py
roborambo/tools/chat.py
roborambo/tools/expertask.py
roborambo/tools/file.py
roborambo/tools/graphql.py
roborambo/tools/image.py
roborambo/tools/inspector.py
roborambo/tools/internal_schedule.py
roborambo/tools/knowledgebase.py
roborambo/tools/prompting.py
roborambo/tools/tool.py
roborambo/tools/util.py
roborambo/tools/vectorstore.py
roborambo/tools/web.py
roborambo-0.0.1.dist-info/METADATA
roborambo-0.0.1.dist-info/WHEEL
roborambo-0.0.1.dist-info/entry_points.txt
roborambo-0.0.1.dist-info/top_level.txt
roborambo-0.0.1.dist-info/RECORD
