Metadata-Version: 2.4
Name: roborambo
Version: 0.0.1
Summary: Dead simple framework to turn LLMs into potentially useful chatbots
Author: Keyton Stanier
License: idfk yet
Keywords: assistant,agent,bot,chatbot,rag,vectorstore,gpt,nothingburger,nothing,burger,llm,chain,text-generation
Requires-Python: >=3.9
Requires-Dist: python-dotenv
Requires-Dist: pandoc
Requires-Dist: chromadb
Requires-Dist: psycopg2-binary
Provides-Extra: zulip
Requires-Dist: zulip; extra == "zulip"
